aio_goodreads/__init__.py
aio_goodreads/client.py
aio_goodreads/types/__init__.py
aio_goodreads/types/author.py
aio_goodreads/types/book.py
aio_goodreads/utils/__init__.py
aio_goodreads/utils/exceptions.py
aio_goodreads-0.1.1.dist-info/LICENSE
aio_goodreads-0.1.1.dist-info/WHEEL
aio_goodreads-0.1.1.dist-info/METADATA
aio_goodreads-0.1.1.dist-info/RECORD
